<?xml version="1.0" encoding="UTF-8"?>
<monster name="Dino" nameDescription="a Dino" race="blood" experience="200" speed="400" manacost="200">
	<health now="50" max="50" />
	<look type="6" corpse="6081" />
	<targetchange interval="4000" chance="0" />
	<flags>
		<flag isSaga="0" />
		<flag isSagaNumber="0" />
		<flag summonable="1" />
		<flag attackable="1" />
		<flag hostile="1" />
		<flag illusionable="1" />
		<flag convinceable="1" />
		<flag pushable="1" />
		<flag canpushitems="0" />
		<flag canpushcreatures="0" />
		<flag targetdistance="1" />
		<flag staticattack="90" />
		<flag runonhealth="5" />
		<flag canwalkonenergy="0" />
		<flag canwalkonfire="0" />
		<flag canwalkonpoison="0" />
	</flags>

	<attacks>
		<attack name="melee" interval="2000" min="-15" max="-30" />
	</attacks>
	<defenses armor="1" defense="1" />
	<elements>
		<element earthPercent="20" />
		<element holyPercent="20" />
		<element icePercent="-10" />
		<element deathPercent="-10" />
	</elements>
	<voices interval="1000" chance="10">
		<voice sentence="Wrr!" />
		<voice sentence="Wrr Wrr!" />
	</voices>
	<loot>
		<item name="zeni" countmax="10" chance="80000" />
	</loot>
</monster>
